[
    {
        "技能名称": "八艘跳跃",
        "HP消耗量": 0.25,
        "目标": "全体",
        "数值伤害": 40,
        "打击次数": 8,
        "命中几率": 75,
        "暴击机率": 5,
        "效果": null,
        "技能独有": "易经",
        "描述": "对所有敌人造成8次物理属性的少量伤害",
        "校正伤害": 50.6,
        "平均伤害": 50.6,
        "ID (Dec)": "",
        "SP消耗量": "",
        "属性": "物理"
    },
    {
        "技能名称": "化妆舞会",
        "HP消耗量": 0.25,
        "目标": "单体",
        "数值伤害": 300,
        "打击次数": 2,
        "命中几率": 90,
        "暴击机率": 30,
        "效果": null,
        "技能独有": "艾拉",
        "描述": "对一名敌人造成2次物理属性的特大伤害",
        "校正伤害": 34.64,
        "平均伤害": 34.64,
        "ID (Dec)": "",
        "SP消耗量": "",
        "属性": "物理"
    },
    {
        "技能名称": "弦艺猛兽",
        "HP消耗量": 0.2,
        "目标": "单体",
        "数值伤害": 1200,
        "打击次数": 1,
        "命中几率": 90,
        "暴击机率": 5,
        "效果": "自我攻击下降",
        "技能独有": "阿里阿德涅(贼神)",
        "描述": "对一名敌人造成物理属性的超特大伤害 但使用后会使攻击力下降90%",
        "校正伤害": 34.64,
        "平均伤害": 34.64,
        "ID (Dec)": "",
        "SP消耗量": "",
        "属性": "物理"
    },
    {
        "技能名称": "巴力神矛",
        "HP消耗量": 0.25,
        "目标": "单体",
        "数值伤害": 100,
        "打击次数": 3,
        "命中几率": 95,
        "暴击机率": 10,
        "效果": null,
        "技能独有": "巴力",
        "描述": "对一名敌人造成3次高命中率物理属性的中量伤害",
        "校正伤害": 30,
        "平均伤害": 30.0,
        "ID (Dec)": "",
        "SP消耗量": "",
        "属性": "物理"
    },
    {
        "技能名称": "神之手",
        "HP消耗量": 0.25,
        "目标": "单体",
        "数值伤害": 800,
        "打击次数": 1,
        "命中几率": 90,
        "暴击机率": 15,
        "效果": null,
        "技能独有": "No",
        "描述": "对一名敌人造成物理属性的超特大伤害",
        "校正伤害": 28.28,
        "平均伤害": 28.28,
        "ID (Dec)": "",
        "SP消耗量": "",
        "属性": "物理"
    },
    {
        "技能名称": "烈焰魔剑",
        "HP消耗量": 0.25,
        "目标": "单体",
        "数值伤害": 800,
        "打击次数": 1,
        "命中几率": 98,
        "暴击机率": 0,
        "效果": null,
        "技能独有": "洛基",
        "描述": "对一名敌人造成物理属性的超特大伤害",
        "校正伤害": 28.28,
        "平均伤害": 28.28,
        "ID (Dec)": "",
        "SP消耗量": "",
        "属性": "物理"
    },
    {
        "技能名称": "虚无艺术",
        "HP消耗量": 0.2,
        "目标": "全体",
        "数值伤害": 300,
        "打击次数": 1641081600000,
        "命中几率": 80,
        "暴击机率": 30,
        "效果": null,
        "技能独有": "雅典娜(贼神)",
        "描述": "对所有敌人造成1-2次高暴击率物理属性的特大伤害",
        "校正伤害": "17.32/34.64",
        "平均伤害": 25.98,
        "ID (Dec)": "",
        "SP消耗量": "",
        "属性": "物理"
    },
    {
        "技能名称": "十文字斩",
        "HP消耗量": 0.2,
        "目标": "单体",
        "数值伤害": 160,
        "打击次数": 2,
        "命中几率": 99,
        "暴击机率": 20,
        "效果": null,
        "技能独有": "伊邪那歧(贼神)",
        "描述": "对一名敌人造成2次高命中率物理属性的大量伤害",
        "校正伤害": 25.3,
        "平均伤害": 25.3,
        "ID (Dec)": "",
        "SP消耗量": "",
        "属性": "物理"
    },
    {
        "技能名称": "勇气之击",
        "HP消耗量": 0.24,
        "目标": "单体",
        "数值伤害": 600,
        "打击次数": 1,
        "命中几率": 90,
        "暴击机率": 35,
        "效果": null,
        "技能独有": "No",
        "描述": "对一名敌人造成物理属性的超特大伤害",
        "校正伤害": 24.49,
        "平均伤害": 24.49,
        "ID (Dec)": "",
        "SP消耗量": "",
        "属性": "物理"
    },
    {
        "技能名称": "刹那五月雨斩",
        "HP消耗量": 0.2,
        "目标": "单体",
        "数值伤害": 90,
        "打击次数": 1643846400000,
        "命中几率": 85,
        "暴击机率": 5,
        "效果": null,
        "技能独有": "No",
        "描述": "对一名敌人造成2-3次物理属性的中量伤害",
        "校正伤害": "18.97/28.46",
        "平均伤害": 23.72,
        "ID (Dec)": "",
        "SP消耗量": "",
        "属性": "物理"
    },
    {
        "技能名称": "火神之击",
        "HP消耗量": 0.24,
        "目标": "全体",
        "数值伤害": 110,
        "打击次数": 1641168000000,
        "命中几率": 80,
        "暴击机率": 5,
        "效果": null,
        "技能独有": "No",
        "描述": "对所有敌人造成1-3次物理属性的中量伤害",
        "校正伤害": "10.49/20.98/31.46",
        "平均伤害": 20.98,
        "ID (Dec)": "",
        "SP消耗量": "",
        "属性": "物理"
    },
    {
        "技能名称": "加特林重击",
        "HP消耗量": 0.16,
        "目标": "单体",
        "数值伤害": 30,
        "打击次数": 1646352000000,
        "命中几率": 90,
        "暴击机率": 5,
        "效果": null,
        "技能独有": "No",
        "描述": "对一名敌人造成3-4次物理属性的少量伤害",
        "校正伤害": "16.43/21.91",
        "平均伤害": 19.17,
        "ID (Dec)": "",
        "SP消耗量": "",
        "属性": "物理"
    },
    {
        "技能名称": "剑之舞",
        "HP消耗量": 0.21,
        "目标": "单体",
        "数值伤害": 360,
        "打击次数": 1,
        "命中几率": 90,
        "暴击机率": 40,
        "效果": null,
        "技能独有": "No",
        "描述": "对一名敌人造成高暴击率物理属性的超特大伤害",
        "校正伤害": 18.97,
        "平均伤害": 18.97,
        "ID (Dec)": "",
        "SP消耗量": "",
        "属性": "物理"
    },
    {
        "技能名称": "巨人之战",
        "HP消耗量": 0.25,
        "目标": "全体",
        "数值伤害": 350,
        "打击次数": 1,
        "命中几率": 85,
        "暴击机率": 5,
        "效果": null,
        "技能独有": "No",
        "描述": "对所有敌人造成物理属性的超特大伤害",
        "校正伤害": 18.71,
        "平均伤害": 18.71,
        "ID (Dec)": "",
        "SP消耗量": "",
        "属性": "物理"
    },
    {
        "技能名称": "五月雨斩",
        "HP消耗量": 0.17,
        "目标": "单体",
        "数值伤害": 20,
        "打击次数": 1646438400000,
        "命中几率": 85,
        "暴击机率": 5,
        "效果": null,
        "技能独有": "No",
        "描述": "对一名敌人造成3-5次物理属性的极小伤害",
        "校正伤害": "13.42/17.89/22.36",
        "平均伤害": 17.89,
        "ID (Dec)": "",
        "SP消耗量": "",
        "属性": "物理"
    },
    {
        "技能名称": "死神大镰斩",
        "HP消耗量": 0.2,
        "目标": "单体",
        "数值伤害": 300,
        "打击次数": 1,
        "命中几率": 90,
        "暴击机率": 5,
        "效果": "恐惧 (55%)",
        "技能独有": "No",
        "描述": "对一名敌人造成物理属性的特大伤害 且有中概率使其陷入恐惧状态",
        "校正伤害": 17.32,
        "平均伤害": 17.32,
        "ID (Dec)": "",
        "SP消耗量": "",
        "属性": "物理"
    },
    {
        "技能名称": "百万吨袭击",
        "HP消耗量": 0.16,
        "目标": "单体",
        "数值伤害": 300,
        "打击次数": 1,
        "命中几率": 85,
        "暴击机率": 25,
        "效果": null,
        "技能独有": "No",
        "描述": "对一名敌人造成物理属性的特大伤害",
        "校正伤害": 17.32,
        "平均伤害": 17.32,
        "ID (Dec)": "",
        "SP消耗量": "",
        "属性": "物理"
    },
    {
        "技能名称": "死亡界限",
        "HP消耗量": 0.22,
        "目标": "全体",
        "数值伤害": 100,
        "打击次数": 1641081600000,
        "命中几率": 80,
        "暴击机率": 10,
        "效果": null,
        "技能独有": "No",
        "描述": "对所有敌人造成1-2次物理属性的中量伤害",
        "校正伤害": "10/20",
        "平均伤害": 15.0,
        "ID (Dec)": "",
        "SP消耗量": "",
        "属性": "物理"
    },
    {
        "技能名称": "死亡游戏",
        "HP消耗量": 0.18,
        "目标": "单体",
        "数值伤害": 220,
        "打击次数": 1,
        "命中几率": 90,
        "暴击机率": 5,
        "效果": null,
        "技能独有": "No",
        "描述": "对一名敌人造成物理属性的特大伤害 在换手时威力上升50%",
        "校正伤害": 14.83,
        "平均伤害": 14.83,
        "ID (Dec)": "",
        "SP消耗量": "",
        "属性": "物理"
    },
    {
        "技能名称": "空间杀法",
        "HP消耗量": 0.23,
        "目标": "全体",
        "数值伤害": 210,
        "打击次数": 1,
        "命中几率": 80,
        "暴击机率": 10,
        "效果": null,
        "技能独有": "No",
        "描述": "对所有敌人造成物理属性的特大伤害",
        "校正伤害": 14.49,
        "平均伤害": 14.49,
        "ID (Dec)": "",
        "SP消耗量": "",
        "属性": "物理"
    },
    {
        "技能名称": "电光石火",
        "HP消耗量": 0.17,
        "目标": "全体",
        "数值伤害": 20,
        "打击次数": 1643932800000,
        "命中几率": 70,
        "暴击机率": 10,
        "效果": null,
        "技能独有": "No",
        "描述": "对所有敌人造成2-4次物理属性的极小伤害",
        "校正伤害": "8.94/13.42/17.89",
        "平均伤害": 13.42,
        "ID (Dec)": "",
        "SP消耗量": "",
        "属性": "物理"
    },
    {
        "技能名称": "二连牙",
        "HP消耗量": 0.1,
        "目标": "单体",
        "数值伤害": 40,
        "打击次数": 2,
        "命中几率": 90,
        "暴击机率": 5,
        "效果": null,
        "技能独有": "No",
        "描述": "对一名敌人造成2次物理属性的少量伤害",
        "校正伤害": 12.65,
        "平均伤害": 12.65,
        "ID (Dec)": "",
        "SP消耗量": "",
        "属性": "物理"
    },
    {
        "技能名称": "炽热波浪",
        "HP消耗量": 0.2,
        "目标": "全体",
        "数值伤害": 150,
        "打击次数": 1,
        "命中几率": 80,
        "暴击机率": 5,
        "效果": null,
        "技能独有": "No",
        "描述": "对所有敌人造成物理属性的大量伤害",
        "校正伤害": 12.25,
        "平均伤害": 12.25,
        "ID (Dec)": "",
        "SP消耗量": "",
        "属性": "物理"
    },
    {
        "技能名称": "杀戮突袭",
        "HP消耗量": 0.14,
        "目标": "单体",
        "数值伤害": 40,
        "打击次数": 1641168000000,
        "命中几率": 90,
        "暴击机率": 5,
        "效果": null,
        "技能独有": "No",
        "描述": "对一名敌人造成1-3次物理属性的少量伤害",
        "校正伤害": "6.32/12.65/18.97",
        "平均伤害": 12.65,
        "ID (Dec)": "",
        "SP消耗量": "",
        "属性": "物理"
    },
    {
        "技能名称": "加倍斩击",
        "HP消耗量": 0.14,
        "目标": "单体",
        "数值伤害": 140,
        "打击次数": 1,
        "命中几率": 90,
        "暴击机率": 5,
        "效果": null,
        "技能独有": "No",
        "描述": "对一名敌人造成物理属性的大量伤害 在换手时威力上升50%",
        "校正伤害": 11.83,
        "平均伤害": 11.83,
        "ID (Dec)": "",
        "SP消耗量": "",
        "属性": "物理"
    },
    {
        "技能名称": "俯冲突击",
        "HP消耗量": 0.13,
        "目标": "单体",
        "数值伤害": 130,
        "打击次数": 1,
        "命中几率": 90,
        "暴击机率": 20,
        "效果": null,
        "技能独有": "No",
        "描述": "对一名敌人造成物理属性的大量伤害",
        "校正伤害": 11.4,
        "平均伤害": 11.4,
        "ID (Dec)": "",
        "SP消耗量": "",
        "属性": "物理"
    },
    {
        "技能名称": "负面意识堆栈",
        "HP消耗量": 0.12,
        "目标": "单体",
        "数值伤害": 120,
        "打击次数": 1,
        "命中几率": 90,
        "暴击机率": 3,
        "效果": "绝望 (35%)",
        "技能独有": "No",
        "描述": "对一名敌人造成物理属性的大量伤害 且有中概率使其陷入绝望状态",
        "校正伤害": 10.95,
        "平均伤害": 10.95,
        "ID (Dec)": "",
        "SP消耗量": "",
        "属性": "物理"
    },
    {
        "技能名称": "血祭",
        "HP消耗量": 0.22,
        "目标": "全体",
        "数值伤害": 120,
        "打击次数": 1,
        "命中几率": 80,
        "暴击机率": 5,
        "效果": "恐惧 (25%)",
        "技能独有": "No",
        "描述": "对所有敌人造成物理属性的大量伤害 且有低概率使其陷入恐惧状态",
        "校正伤害": 10.95,
        "平均伤害": 10.95,
        "ID (Dec)": "",
        "SP消耗量": "",
        "属性": "物理"
    },
    {
        "技能名称": "碎脑击",
        "HP消耗量": 0.22,
        "目标": "全体",
        "数值伤害": 120,
        "打击次数": 1,
        "命中几率": 80,
        "暴击机率": 5,
        "效果": "洗脑 (25%)",
        "技能独有": "No",
        "描述": "对所有敌人造成物理属性的大量伤害 且有低概率使其陷入洗脑状态",
        "校正伤害": 10.95,
        "平均伤害": 10.95,
        "ID (Dec)": "",
        "SP消耗量": "",
        "属性": "物理"
    },
    {
        "技能名称": "横冲直撞",
        "HP消耗量": 0.13,
        "目标": "全体",
        "数值伤害": 30,
        "打击次数": 1641168000000,
        "命中几率": 70,
        "暴击机率": 10,
        "效果": null,
        "技能独有": "No",
        "描述": "对所有敌人造成1-3次物理属性的少量伤害",
        "校正伤害": "5.48/10.95/16.43",
        "平均伤害": 10.95,
        "ID (Dec)": "",
        "SP消耗量": "",
        "属性": "物理"
    },
    {
        "技能名称": "心念切断",
        "HP消耗量": 0.19,
        "目标": "全体",
        "数值伤害": 110,
        "打击次数": 1,
        "命中几率": 80,
        "暴击机率": 5,
        "效果": "混乱 (25%)",
        "技能独有": "No",
        "描述": "对所有敌人造成物理属性的中量伤害 且有低概率使其陷入混乱状态",
        "校正伤害": 10.49,
        "平均伤害": 10.49,
        "ID (Dec)": "",
        "SP消耗量": "",
        "属性": "物理"
    },
    {
        "技能名称": "绝望敲打",
        "HP消耗量": 0.21,
        "目标": "全体",
        "数值伤害": 110,
        "打击次数": 1,
        "命中几率": 80,
        "暴击机率": 5,
        "效果": "绝望 (25%)",
        "技能独有": "No",
        "描述": "对所有敌人造成物理属性的中量伤害 且有低概率使其陷入绝望状态",
        "校正伤害": 10.49,
        "平均伤害": 10.49,
        "ID (Dec)": "",
        "SP消耗量": "",
        "属性": "物理"
    },
    {
        "技能名称": "烈风波",
        "HP消耗量": 0.18,
        "目标": "全体",
        "数值伤害": 110,
        "打击次数": 1,
        "命中几率": 80,
        "暴击机率": 5,
        "效果": null,
        "技能独有": "No",
        "描述": "对所有敌人造成物理属性的中量伤害",
        "校正伤害": 10.49,
        "平均伤害": 10.49,
        "ID (Dec)": "",
        "SP消耗量": "",
        "属性": "物理"
    },
    {
        "技能名称": "穷鼠之牙",
        "HP消耗量": 0.1,
        "目标": "单体",
        "数值伤害": 100,
        "打击次数": 1,
        "命中几率": 85,
        "暴击机率": 35,
        "效果": null,
        "技能独有": "No",
        "描述": "对一名敌人造成物理属性的中量伤害 在被包围时威力上升50%",
        "校正伤害": 10,
        "平均伤害": 10.0,
        "ID (Dec)": "",
        "SP消耗量": "",
        "属性": "物理"
    },
    {
        "技能名称": "骇鸦",
        "HP消耗量": 0.08,
        "目标": "单体",
        "数值伤害": 100,
        "打击次数": 1,
        "命中几率": 90,
        "暴击机率": 5,
        "效果": "恐惧 (35%)",
        "技能独有": "No",
        "描述": "对一名敌人造成物理属性的少量伤害 且有中概率使其陷入恐惧状态",
        "校正伤害": 10,
        "平均伤害": 10.0,
        "ID (Dec)": "",
        "SP消耗量": "",
        "属性": "物理"
    },
    {
        "技能名称": "倒栽痛击",
        "HP消耗量": 0.1,
        "目标": "单体",
        "数值伤害": 100,
        "打击次数": 1,
        "命中几率": 90,
        "暴击机率": 5,
        "效果": "混乱 (35%)",
        "技能独有": "No",
        "描述": "对一名敌人造成物理属性的中量伤害 且有中概率使其陷入混乱状态",
        "校正伤害": 10,
        "平均伤害": 10.0,
        "ID (Dec)": "",
        "SP消耗量": "",
        "属性": "物理"
    },
    {
        "技能名称": "烈击巨锤",
        "HP消耗量": 0.1,
        "目标": "单体",
        "数值伤害": 100,
        "打击次数": 1,
        "命中几率": 90,
        "暴击机率": 5,
        "效果": "晕眩 (35%)",
        "技能独有": "No",
        "描述": "对一名敌人造成物理属性的中量伤害 且有中概率使其陷入晕眩状态",
        "校正伤害": 10,
        "平均伤害": 10.0,
        "ID (Dec)": "",
        "SP消耗量": "",
        "属性": "物理"
    },
    {
        "技能名称": "闪光炸弹",
        "HP消耗量": 0.19,
        "目标": "全体",
        "数值伤害": 100,
        "打击次数": 1,
        "命中几率": 80,
        "暴击机率": 5,
        "效果": "晕眩 (25%)",
        "技能独有": "No",
        "描述": "对所有敌人造成物理属性的中量伤害 且有低概率使其陷入晕眩状态",
        "校正伤害": 10,
        "平均伤害": 10.0,
        "ID (Dec)": "",
        "SP消耗量": "",
        "属性": "物理"
    },
    {
        "技能名称": "威力斩击",
        "HP消耗量": 0.1,
        "目标": "单体",
        "数值伤害": 100,
        "打击次数": 1,
        "命中几率": 85,
        "暴击机率": 20,
        "效果": null,
        "技能独有": "No",
        "描述": "对一名敌人造成物理属性的中量伤害",
        "校正伤害": 10,
        "平均伤害": 10.0,
        "ID (Dec)": "",
        "SP消耗量": "",
        "属性": "物理"
    },
    {
        "技能名称": "大斩断",
        "HP消耗量": 0.09,
        "目标": "单体",
        "数值伤害": 90,
        "打击次数": 1,
        "命中几率": 90,
        "暴击机率": 30,
        "效果": null,
        "技能独有": "No",
        "描述": "对一名敌人造成物理属性的中量伤害 在换手时威力上升50%",
        "校正伤害": 9.49,
        "平均伤害": 9.49,
        "ID (Dec)": "",
        "SP消耗量": "",
        "属性": "物理"
    },
    {
        "技能名称": "歇斯底里掌掴",
        "HP消耗量": 0.09,
        "目标": "单体",
        "数值伤害": 80,
        "打击次数": 1,
        "命中几率": 90,
        "暴击机率": 5,
        "效果": "狂怒 (35%)",
        "技能独有": "No",
        "描述": "对一名敌人造成物理属性的中量伤害 且有中概率使其陷入狂怒状态",
        "校正伤害": 8.84,
        "平均伤害": 8.84,
        "ID (Dec)": "",
        "SP消耗量": "",
        "属性": "物理"
    },
    {
        "技能名称": "头脑震撼",
        "HP消耗量": 0.09,
        "目标": "单体",
        "数值伤害": 80,
        "打击次数": 1,
        "命中几率": 90,
        "暴击机率": 5,
        "效果": "洗脑 (35%)",
        "技能独有": "No",
        "描述": "对一名敌人造成物理属性的中量伤害 且有中概率使其陷入洗脑状态",
        "校正伤害": 8.94,
        "平均伤害": 8.94,
        "ID (Dec)": "",
        "SP消耗量": "",
        "属性": "物理"
    },
    {
        "技能名称": "头锤",
        "HP消耗量": 0.09,
        "目标": "单体",
        "数值伤害": 80,
        "打击次数": 1,
        "命中几率": 90,
        "暴击机率": 5,
        "效果": "遗忘 (35%)",
        "技能独有": "No",
        "描述": "对一名敌人造成物理属性的中量伤害 且有中概率使其陷入遗忘状态",
        "校正伤害": 8.94,
        "平均伤害": 8.94,
        "ID (Dec)": "",
        "SP消耗量": "",
        "属性": "物理"
    },
    {
        "技能名称": "永眠突袭",
        "HP消耗量": 0.16,
        "目标": "全体",
        "数值伤害": 80,
        "打击次数": 1,
        "命中几率": 80,
        "暴击机率": 5,
        "效果": "睡眠 (25%)",
        "技能独有": "No",
        "描述": "对所有敌人造成物理属性的中量伤害 且有低概率使其陷入睡眠状态",
        "校正伤害": 8.94,
        "平均伤害": 8.94,
        "ID (Dec)": "",
        "SP消耗量": "",
        "属性": "物理"
    },
    {
        "技能名称": "奇迹拳",
        "HP消耗量": 0.08,
        "目标": "单体",
        "数值伤害": 80,
        "打击次数": 1,
        "命中几率": 75,
        "暴击机率": 45,
        "效果": null,
        "技能独有": "No",
        "描述": "对一名敌人造成高暴击率物理属性的中量伤害",
        "校正伤害": 8.94,
        "平均伤害": 8.94,
        "ID (Dec)": "",
        "SP消耗量": "",
        "属性": "物理"
    },
    {
        "技能名称": "奇迹突袭",
        "HP消耗量": 0.16,
        "目标": "全体",
        "数值伤害": 80,
        "打击次数": 1,
        "命中几率": 55,
        "暴击机率": 40,
        "效果": null,
        "技能独有": "迪亚哥",
        "描述": "对所有敌人造成高暴击率物理属性的中量伤害",
        "校正伤害": 8.94,
        "平均伤害": 8.94,
        "ID (Dec)": "",
        "SP消耗量": "",
        "属性": "物理"
    },
    {
        "技能名称": "鬼神乐",
        "HP消耗量": 0.16,
        "目标": "全体",
        "数值伤害": 80,
        "打击次数": 1,
        "命中几率": 80,
        "暴击机率": 5,
        "效果": "狂怒 (25%)",
        "技能独有": "No",
        "描述": "对所有敌人造成物理属性的中量伤害 且有低概率使其陷入狂怒状态",
        "校正伤害": 8.94,
        "平均伤害": 8.94,
        "ID (Dec)": "",
        "SP消耗量": "",
        "属性": "物理"
    },
    {
        "技能名称": "金刚发破",
        "HP消耗量": 0.13,
        "目标": "全体",
        "数值伤害": 80,
        "打击次数": 1,
        "命中几率": 80,
        "暴击机率": 5,
        "效果": null,
        "技能独有": "No",
        "描述": "对所有敌人造成物理属性的中量伤害",
        "校正伤害": 8.94,
        "平均伤害": 8.94,
        "ID (Dec)": "",
        "SP消耗量": "",
        "属性": "物理"
    },
    {
        "技能名称": "忘杀突袭",
        "HP消耗量": 0.15,
        "目标": "全体",
        "数值伤害": 70,
        "打击次数": 1,
        "命中几率": 80,
        "暴击机率": 5,
        "效果": "遗忘 (25%)",
        "技能独有": "No",
        "描述": "对所有敌人造成物理属性的少量伤害 且有低概率使其陷入遗忘状态",
        "校正伤害": 8.37,
        "平均伤害": 8.37,
        "ID (Dec)": "",
        "SP消耗量": "",
        "属性": "物理"
    },
    {
        "技能名称": "斩击",
        "HP消耗量": 0.06,
        "目标": "单体",
        "数值伤害": 65,
        "打击次数": 1,
        "命中几率": 90,
        "暴击机率": 20,
        "效果": null,
        "技能独有": "No",
        "描述": "对一名敌人造成物理属性的少量伤害",
        "校正伤害": 8.06,
        "平均伤害": 8.06,
        "ID (Dec)": "",
        "SP消耗量": "",
        "属性": "物理"
    },
    {
        "技能名称": "突击",
        "HP消耗量": 0.05,
        "目标": "单体",
        "数值伤害": 60,
        "打击次数": 1,
        "命中几率": 90,
        "暴击机率": 20,
        "效果": null,
        "技能独有": "No",
        "描述": "对一名敌人造成物理属性的少量伤害",
        "校正伤害": 7.75,
        "平均伤害": 7.75,
        "ID (Dec)": "",
        "SP消耗量": "",
        "属性": "物理"
    },
    {
        "技能名称": "幸运拳",
        "HP消耗量": 0.03,
        "目标": "单体",
        "数值伤害": 25,
        "打击次数": 1,
        "命中几率": 75,
        "暴击机率": 45,
        "效果": null,
        "技能独有": "No",
        "描述": "对一名敌人造成高暴击率物理属性的极小伤害",
        "校正伤害": 5,
        "平均伤害": 5.0,
        "ID (Dec)": "",
        "SP消耗量": "",
        "属性": "物理"
    },
    {
        "技能名称": "至高魔弹",
        "HP消耗量": 0.24,
        "目标": "全体",
        "数值伤害": 300,
        "打击次数": 1,
        "命中几率": 80,
        "暴击机率": 10,
        "效果": null,
        "技能独有": "No",
        "描述": "对所有敌人造成枪击属性的特大伤害",
        "校正伤害": 17.32,
        "平均伤害": "",
        "ID (Dec)": "",
        "SP消耗量": "",
        "属性": "枪击"
    },
    {
        "技能名称": "三连倒",
        "HP消耗量": 0.16,
        "目标": "全体",
        "数值伤害": 30,
        "打击次数": 3,
        "命中几率": 70,
        "暴击机率": 5,
        "效果": null,
        "技能独有": "No",
        "描述": "对所有敌人造成3次枪击属性的少量伤害",
        "校正伤害": 16.43,
        "平均伤害": "",
        "ID (Dec)": "",
        "SP消耗量": "",
        "属性": "枪击"
    },
    {
        "技能名称": "一枪毙命",
        "HP消耗量": 0.17,
        "目标": "单体",
        "数值伤害": 210,
        "打击次数": 1,
        "命中几率": 90,
        "暴击机率": 40,
        "效果": null,
        "技能独有": "No",
        "描述": "对一名敌人造成高暴击率枪击属性的特大伤害",
        "校正伤害": 14.49,
        "平均伤害": "",
        "ID (Dec)": "",
        "SP消耗量": "",
        "属性": "枪击"
    },
    {
        "技能名称": "双重射击",
        "HP消耗量": 0.12,
        "目标": "单体",
        "数值伤害": 50,
        "打击次数": 2,
        "命中几率": 90,
        "暴击机率": 5,
        "效果": null,
        "技能独有": "No",
        "描述": "对一名敌人造成2次枪击属性的少量伤害",
        "校正伤害": 14.14,
        "平均伤害": "",
        "ID (Dec)": "",
        "SP消耗量": "",
        "属性": "枪击"
    },
    {
        "技能名称": "指弹",
        "HP消耗量": 0.09,
        "目标": "单体",
        "数值伤害": 80,
        "打击次数": 1,
        "命中几率": 90,
        "暴击机率": 30,
        "效果": null,
        "技能独有": "No",
        "描述": "对一名敌人造成枪击属性的中量伤害",
        "校正伤害": 8.94,
        "平均伤害": "",
        "ID (Dec)": "",
        "SP消耗量": "",
        "属性": "枪击"
    },
    {
        "技能名称": "织梦针",
        "HP消耗量": 0.08,
        "目标": "单体",
        "数值伤害": 70,
        "打击次数": 1,
        "命中几率": 90,
        "暴击机率": 5,
        "效果": "睡眠(35%)",
        "技能独有": "No",
        "描述": "对一名敌人造成枪击属性的少量伤害 且有中概率使其陷入睡眠状态",
        "校正伤害": 8.37,
        "平均伤害": "",
        "ID (Dec)": "",
        "SP消耗量": "",
        "属性": "枪击"
    },
    {
        "技能名称": "亚基",
        "SP消耗量": 4,
        "目标": "单体",
        "数值伤害": 40,
        "打击次数": 1,
        "命中几率": 99,
        "效果": "燃烧(25%)",
        "技能独有": "No",
        "描述": "对一名敌人造成火焰属性的少量伤害 偶尔使敌人陷入燃烧状态",
        "校正伤害": 6.32,
        "平均伤害": "",
        "ID (Dec)": "",
        "暴击机率": "",
        "HP消耗量": "",
        "属性": "火焰"
    },
    {
        "技能名称": "亚基拉欧",
        "SP消耗量": 8,
        "目标": "单体",
        "数值伤害": 100,
        "打击次数": 1,
        "命中几率": 99,
        "效果": "燃烧(25%)",
        "技能独有": "No",
        "描述": "对一名敌人造成火焰属性的中量伤害 偶尔使敌人陷入燃烧状态",
        "校正伤害": 10.0,
        "平均伤害": "",
        "ID (Dec)": "",
        "暴击机率": "",
        "HP消耗量": "",
        "属性": "火焰"
    },
    {
        "技能名称": "亚基达因",
        "SP消耗量": 12,
        "目标": "单体",
        "数值伤害": 160,
        "打击次数": 1,
        "命中几率": 99,
        "效果": "燃烧(25%)",
        "技能独有": "No",
        "描述": "对一名敌人造成火焰属性的大量伤害 偶尔使敌人陷入燃烧状态",
        "校正伤害": 12.65,
        "平均伤害": "",
        "ID (Dec)": "",
        "暴击机率": "",
        "HP消耗量": "",
        "属性": "火焰"
    },
    {
        "技能名称": "炼狱",
        "SP消耗量": 48,
        "目标": "单体",
        "数值伤害": 200,
        "打击次数": 1,
        "命中几率": 98,
        "效果": "燃烧(26%)",
        "技能独有": "No",
        "描述": "对一名敌人造成火焰属性的特大伤害 偶尔使敌人陷入燃烧状态",
        "校正伤害": 14.14,
        "平均伤害": "",
        "ID (Dec)": "",
        "暴击机率": "",
        "HP消耗量": "",
        "属性": "火焰"
    },
    {
        "技能名称": "玛哈拉基",
        "SP消耗量": 10,
        "目标": "全体",
        "数值伤害": 40,
        "打击次数": 1,
        "命中几率": 95,
        "效果": "燃烧(20%)",
        "技能独有": "No",
        "描述": "对所有敌人造成火焰属性的少量伤害 偶尔使敌人陷入燃烧状态",
        "校正伤害": 6.32,
        "平均伤害": "",
        "ID (Dec)": "",
        "暴击机率": "",
        "HP消耗量": "",
        "属性": "火焰"
    },
    {
        "技能名称": "玛哈拉基翁",
        "SP消耗量": 16,
        "目标": "全体",
        "数值伤害": 100,
        "打击次数": 1,
        "命中几率": 95,
        "效果": "燃烧(20%)",
        "技能独有": "No",
        "描述": "对所有敌人造成火焰属性的中量伤害 偶尔使敌人陷入燃烧状态",
        "校正伤害": 10.0,
        "平均伤害": "",
        "ID (Dec)": "",
        "暴击机率": "",
        "HP消耗量": "",
        "属性": "火焰"
    },
    {
        "技能名称": "玛哈拉基达因",
        "SP消耗量": 22,
        "目标": "全体",
        "数值伤害": 160,
        "打击次数": 1,
        "命中几率": 95,
        "效果": "燃烧(20%)",
        "技能独有": "No",
        "描述": "对所有敌人造成火焰属性的大量伤害 偶尔使敌人陷入燃烧状态",
        "校正伤害": 12.65,
        "平均伤害": "",
        "ID (Dec)": "",
        "暴击机率": "",
        "HP消耗量": "",
        "属性": "火焰"
    },
    {
        "技能名称": "大燃烧",
        "SP消耗量": 54,
        "目标": "全体",
        "数值伤害": 180,
        "打击次数": 1,
        "命中几率": 95,
        "效果": "燃烧(24%)",
        "技能独有": "No",
        "描述": "对所有敌人造成火焰属性的特大伤害 偶尔使敌人陷入燃烧状态",
        "校正伤害": 13.42,
        "平均伤害": "",
        "ID (Dec)": "",
        "暴击机率": "",
        "HP消耗量": "",
        "属性": "火焰"
    },
    {
        "技能名称": "泰坦之战",
        "SP消耗量": 34,
        "目标": "全体",
        "数值伤害": 210,
        "打击次数": 1,
        "命中几率": 90,
        "效果": "恐惧(70%)",
        "技能独有": "阿斯忒里俄斯 (贼神)",
        "描述": "对所有敌人造成火焰属性的特大伤害 且有高概率陷入恐惧状态",
        "校正伤害": 14.49,
        "平均伤害": "",
        "ID (Dec)": "",
        "暴击机率": "",
        "HP消耗量": "",
        "属性": "火焰"
    },
    {
        "技能名称": "布芙",
        "SP消耗量": 4,
        "目标": "单体",
        "数值伤害": 40,
        "打击次数": 1,
        "命中几率": 99,
        "效果": "冻结 (25%)",
        "技能独有": "No",
        "描述": "对一名敌人造成冰冻属性的少量伤害 偶尔使敌人陷入冻结状态",
        "校正伤害": 6.32,
        "平均伤害": "",
        "ID (Dec)": "",
        "暴击机率": "",
        "HP消耗量": "",
        "属性": "冰冻"
    },
    {
        "技能名称": "布芙拉",
        "SP消耗量": 8,
        "目标": "单体",
        "数值伤害": 100,
        "打击次数": 1,
        "命中几率": 99,
        "效果": "冻结 (25%)",
        "技能独有": "No",
        "描述": "对一名敌人造成冰冻属性的中量伤害 偶尔使敌人陷入冻结状态",
        "校正伤害": 10.0,
        "平均伤害": "",
        "ID (Dec)": "",
        "暴击机率": "",
        "HP消耗量": "",
        "属性": "冰冻"
    },
    {
        "技能名称": "布芙达因",
        "SP消耗量": 12,
        "目标": "单体",
        "数值伤害": 160,
        "打击次数": 1,
        "命中几率": 99,
        "效果": "冻结 (25%)",
        "技能独有": "No",
        "描述": "对一名敌人造成冰冻属性的大量伤害 偶尔使敌人陷入冻结状态",
        "校正伤害": 12.65,
        "平均伤害": "",
        "ID (Dec)": "",
        "暴击机率": "",
        "HP消耗量": "",
        "属性": "冰冻"
    },
    {
        "技能名称": "钻石星尘",
        "SP消耗量": 48,
        "目标": "单体",
        "数值伤害": 200,
        "打击次数": 1,
        "命中几率": 98,
        "效果": "冻结 (26%)",
        "技能独有": "No",
        "描述": "对一名敌人造成冰冻属性的特大伤害 偶尔使敌人陷入冻结状态",
        "校正伤害": 14.14,
        "平均伤害": "",
        "ID (Dec)": "",
        "暴击机率": "",
        "HP消耗量": "",
        "属性": "冰冻"
    },
    {
        "技能名称": "玛哈布芙",
        "SP消耗量": 10,
        "目标": "全体",
        "数值伤害": 40,
        "打击次数": 1,
        "命中几率": 95,
        "效果": "冻结 (20%)",
        "技能独有": "No",
        "描述": "对所有敌人造成冰冻属性的少量伤害 偶尔使敌人陷入冻结状态",
        "校正伤害": 6.32,
        "平均伤害": "",
        "ID (Dec)": "",
        "暴击机率": "",
        "HP消耗量": "",
        "属性": "冰冻"
    },
    {
        "技能名称": "玛哈布芙拉",
        "SP消耗量": 16,
        "目标": "全体",
        "数值伤害": 100,
        "打击次数": 1,
        "命中几率": 95,
        "效果": "冻结 (20%)",
        "技能独有": "No",
        "描述": "对所有敌人造成冰冻属性的中量伤害 偶尔使敌人陷入冻结状态",
        "校正伤害": 10.0,
        "平均伤害": "",
        "ID (Dec)": "",
        "暴击机率": "",
        "HP消耗量": "",
        "属性": "冰冻"
    },
    {
        "技能名称": "玛哈布芙达因",
        "SP消耗量": 22,
        "目标": "全体",
        "数值伤害": 160,
        "打击次数": 1,
        "命中几率": 95,
        "效果": "冻结 (20%)",
        "技能独有": "No",
        "描述": "对所有敌人造成冰冻属性的大量伤害 偶尔使敌人陷入冻结状态",
        "校正伤害": 12.65,
        "平均伤害": "",
        "ID (Dec)": "",
        "暴击机率": "",
        "HP消耗量": "",
        "属性": "冰冻"
    },
    {
        "技能名称": "大冰河时期",
        "SP消耗量": 54,
        "目标": "全体",
        "数值伤害": 180,
        "打击次数": 1,
        "命中几率": 95,
        "效果": "冻结 (24%)",
        "技能独有": "No",
        "描述": "对所有敌人造成冰冻属性的特大伤害 偶尔使敌人陷入冻结状态",
        "校正伤害": 13.42,
        "平均伤害": "",
        "ID (Dec)": "",
        "暴击机率": "",
        "HP消耗量": "",
        "属性": "冰冻"
    },
    {
        "技能名称": "吉欧",
        "SP消耗量": 4,
        "目标": "单体",
        "数值伤害": 40,
        "打击次数": 1,
        "命中几率": 99,
        "效果": "触电 (25%)",
        "技能独有": "No",
        "描述": "对一名敌人造成电击属性的少量伤害 偶尔使敌人陷入触电状态",
        "校正伤害": 6.32,
        "平均伤害": "",
        "ID (Dec)": "",
        "暴击机率": "",
        "HP消耗量": "",
        "属性": "电击"
    },
    {
        "技能名称": "吉欧加",
        "SP消耗量": 8,
        "目标": "单体",
        "数值伤害": 100,
        "打击次数": 1,
        "命中几率": 99,
        "效果": "触电 (25%)",
        "技能独有": "No",
        "描述": "对一名敌人造成电击属性的中量伤害 偶尔使敌人陷入触电状态",
        "校正伤害": 10.0,
        "平均伤害": "",
        "ID (Dec)": "",
        "暴击机率": "",
        "HP消耗量": "",
        "属性": "电击"
    },
    {
        "技能名称": "吉欧达因",
        "SP消耗量": 12,
        "目标": "单体",
        "数值伤害": 160,
        "打击次数": 1,
        "命中几率": 99,
        "效果": "触电 (25%)",
        "技能独有": "No",
        "描述": "对一名敌人造成电击属性的大量伤害 偶尔使敌人陷入触电状态",
        "校正伤害": 12.65,
        "平均伤害": "",
        "ID (Dec)": "",
        "暴击机率": "",
        "HP消耗量": "",
        "属性": "电击"
    },
    {
        "技能名称": "真理之雷",
        "SP消耗量": 48,
        "目标": "单体",
        "数值伤害": 200,
        "打击次数": 1,
        "命中几率": 98,
        "效果": "触电 (26%)",
        "技能独有": "No",
        "描述": "对一名敌人造成电击属性的特大伤害 偶尔使敌人陷入触电状态",
        "校正伤害": 14.14,
        "平均伤害": "",
        "ID (Dec)": "",
        "暴击机率": "",
        "HP消耗量": "",
        "属性": "电击"
    },
    {
        "技能名称": "玛哈吉欧",
        "SP消耗量": 10,
        "目标": "全体",
        "数值伤害": 40,
        "打击次数": 1,
        "命中几率": 95,
        "效果": "触电 (20%)",
        "技能独有": "No",
        "描述": "对所有敌人造成电击属性的少量伤害 偶尔使敌人陷入触电状态",
        "校正伤害": 6.32,
        "平均伤害": "",
        "ID (Dec)": "",
        "暴击机率": "",
        "HP消耗量": "",
        "属性": "电击"
    },
    {
        "技能名称": "玛哈吉欧加",
        "SP消耗量": 16,
        "目标": "全体",
        "数值伤害": 100,
        "打击次数": 1,
        "命中几率": 95,
        "效果": "触电 (20%)",
        "技能独有": "No",
        "描述": "对所有敌人造成电击属性的中量伤害 偶尔使敌人陷入触电状态",
        "校正伤害": 10.0,
        "平均伤害": "",
        "ID (Dec)": "",
        "暴击机率": "",
        "HP消耗量": "",
        "属性": "电击"
    },
    {
        "技能名称": "玛哈吉欧达因",
        "SP消耗量": 22,
        "目标": "全体",
        "数值伤害": 160,
        "打击次数": 1,
        "命中几率": 95,
        "效果": "触电 (20%)",
        "技能独有": "No",
        "描述": "对所有敌人造成电击属性的大量伤害 偶尔使敌人陷入触电状态",
        "校正伤害": 12.65,
        "平均伤害": "",
        "ID (Dec)": "",
        "暴击机率": "",
        "HP消耗量": "",
        "属性": "电击"
    },
    {
        "技能名称": "崇高圣战",
        "SP消耗量": 54,
        "目标": "全体",
        "数值伤害": 180,
        "打击次数": 1,
        "命中几率": 95,
        "效果": "触电 (24%)",
        "技能独有": "No",
        "描述": "对所有敌人造成电击属性的特大伤害 偶尔使敌人陷入触电状态",
        "校正伤害": 13.42,
        "平均伤害": "",
        "ID (Dec)": "",
        "暴击机率": "",
        "HP消耗量": "",
        "属性": "电击"
    },
    {
        "技能名称": "加尔",
        "SP消耗量": 3,
        "目标": "单体",
        "数值伤害": 40,
        "打击次数": 1,
        "命中几率": 99,
        "效果": null,
        "技能独有": "No",
        "描述": "对一名敌人造成疾风属性的少量伤害",
        "校正伤害": 6.32,
        "平均伤害": "",
        "ID (Dec)": "",
        "暴击机率": "",
        "HP消耗量": "",
        "属性": "疾风"
    },
    {
        "技能名称": "加尔拉",
        "SP消耗量": 6,
        "目标": "单体",
        "数值伤害": 100,
        "打击次数": 1,
        "命中几率": 99,
        "效果": null,
        "技能独有": "No",
        "描述": "对一名敌人造成疾风属性的中量伤害",
        "校正伤害": 10.0,
        "平均伤害": "",
        "ID (Dec)": "",
        "暴击机率": "",
        "HP消耗量": "",
        "属性": "疾风"
    },
    {
        "技能名称": "加尔达因",
        "SP消耗量": 10,
        "目标": "单体",
        "数值伤害": 160,
        "打击次数": 1,
        "命中几率": 99,
        "效果": null,
        "技能独有": "No",
        "描述": "对一名敌人造成疾风属性的大量伤害",
        "校正伤害": 12.65,
        "平均伤害": "",
        "ID (Dec)": "",
        "暴击机率": "",
        "HP消耗量": "",
        "属性": "疾风"
    },
    {
        "技能名称": "万物流转",
        "SP消耗量": 42,
        "目标": "单体",
        "数值伤害": 200,
        "打击次数": 1,
        "命中几率": 98,
        "效果": null,
        "技能独有": "No",
        "描述": "对一名敌人造成疾风属性的特大伤害",
        "校正伤害": 14.14,
        "平均伤害": "",
        "ID (Dec)": "",
        "暴击机率": "",
        "HP消耗量": "",
        "属性": "疾风"
    },
    {
        "技能名称": "玛哈加尔",
        "SP消耗量": 8,
        "目标": "全体",
        "数值伤害": 40,
        "打击次数": 1,
        "命中几率": 95,
        "效果": null,
        "技能独有": "No",
        "描述": "对所有敌人造成疾风属性的少量伤害",
        "校正伤害": 6.32,
        "平均伤害": "",
        "ID (Dec)": "",
        "暴击机率": "",
        "HP消耗量": "",
        "属性": "疾风"
    },
    {
        "技能名称": "玛哈加尔拉",
        "SP消耗量": 14,
        "目标": "全体",
        "数值伤害": 100,
        "打击次数": 1,
        "命中几率": 95,
        "效果": null,
        "技能独有": "No",
        "描述": "对所有敌人造成疾风属性的中量伤害",
        "校正伤害": 10.0,
        "平均伤害": "",
        "ID (Dec)": "",
        "暴击机率": "",
        "HP消耗量": "",
        "属性": "疾风"
    },
    {
        "技能名称": "玛哈加尔达因",
        "SP消耗量": 20,
        "目标": "全体",
        "数值伤害": 160,
        "打击次数": 1,
        "命中几率": 95,
        "效果": null,
        "技能独有": "No",
        "描述": "对所有敌人造成疾风属性的大量伤害",
        "校正伤害": 12.65,
        "平均伤害": "",
        "ID (Dec)": "",
        "暴击机率": "",
        "HP消耗量": "",
        "属性": "疾风"
    },
    {
        "技能名称": "真空波",
        "SP消耗量": 48,
        "目标": "全体",
        "数值伤害": 200,
        "打击次数": 1,
        "命中几率": 95,
        "效果": null,
        "技能独有": "No",
        "描述": "对所有敌人造成疾风属性的特大伤害",
        "校正伤害": 14.14,
        "平均伤害": "",
        "ID (Dec)": "",
        "暴击机率": "",
        "HP消耗量": "",
        "属性": "疾风"
    },
    {
        "技能名称": "芙雷",
        "SP消耗量": 4,
        "目标": "单体",
        "数值伤害": 40,
        "打击次数": 1,
        "命中几率": 99,
        "效果": null,
        "技能独有": "No",
        "描述": "对一名敌人造成核热属性的少量伤害",
        "校正伤害": 6.32,
        "平均伤害": "",
        "ID (Dec)": "",
        "暴击机率": "",
        "HP消耗量": "",
        "属性": "核热"
    },
    {
        "技能名称": "芙雷拉",
        "SP消耗量": 8,
        "目标": "单体",
        "数值伤害": 100,
        "打击次数": 1,
        "命中几率": 99,
        "效果": null,
        "技能独有": "No",
        "描述": "对一名敌人造成核热属性的中量伤害",
        "校正伤害": 10.0,
        "平均伤害": "",
        "ID (Dec)": "",
        "暴击机率": "",
        "HP消耗量": "",
        "属性": "核热"
    },
    {
        "技能名称": "芙雷达因",
        "SP消耗量": 12,
        "目标": "单体",
        "数值伤害": 160,
        "打击次数": 1,
        "命中几率": 99,
        "效果": null,
        "技能独有": "No",
        "描述": "对一名敌人造成核热属性的大量伤害",
        "校正伤害": 12.65,
        "平均伤害": "",
        "ID (Dec)": "",
        "暴击机率": "",
        "HP消耗量": "",
        "属性": "核热"
    },
    {
        "技能名称": "原子火焰",
        "SP消耗量": 48,
        "目标": "单体",
        "数值伤害": 200,
        "打击次数": 1,
        "命中几率": 98,
        "效果": null,
        "技能独有": "No",
        "描述": "对一名敌人造成核热属性的特大伤害",
        "校正伤害": 14.14,
        "平均伤害": "",
        "ID (Dec)": "",
        "暴击机率": "",
        "HP消耗量": "",
        "属性": "核热"
    },
    {
        "技能名称": "玛哈芙雷",
        "SP消耗量": 10,
        "目标": "全体",
        "数值伤害": 40,
        "打击次数": 1,
        "命中几率": 95,
        "效果": null,
        "技能独有": "No",
        "描述": "对所有敌人造成核热属性的少量伤害",
        "校正伤害": 6.32,
        "平均伤害": "",
        "ID (Dec)": "",
        "暴击机率": "",
        "HP消耗量": "",
        "属性": "核热"
    },
    {
        "技能名称": "玛哈芙雷拉",
        "SP消耗量": 16,
        "目标": "全体",
        "数值伤害": 100,
        "打击次数": 1,
        "命中几率": 95,
        "效果": null,
        "技能独有": "No",
        "描述": "对所有敌人造成核热属性的中量伤害",
        "校正伤害": 10.0,
        "平均伤害": "",
        "ID (Dec)": "",
        "暴击机率": "",
        "HP消耗量": "",
        "属性": "核热"
    },
    {
        "技能名称": "玛哈芙雷达因",
        "SP消耗量": 22,
        "目标": "全体",
        "数值伤害": 160,
        "打击次数": 1,
        "命中几率": 95,
        "效果": null,
        "技能独有": "No",
        "描述": "对所有敌人造成核热属性的大量伤害",
        "校正伤害": 12.65,
        "平均伤害": "",
        "ID (Dec)": "",
        "暴击机率": "",
        "HP消耗量": "",
        "属性": "核热"
    },
    {
        "技能名称": "宇宙火焰",
        "SP消耗量": 54,
        "目标": "全体",
        "数值伤害": 180,
        "打击次数": 1,
        "命中几率": 95,
        "效果": null,
        "技能独有": "No",
        "描述": "对所有敌人造成核热属性的特大伤害",
        "校正伤害": 13.42,
        "平均伤害": "",
        "ID (Dec)": "",
        "暴击机率": "",
        "HP消耗量": "",
        "属性": "核热"
    },
    {
        "技能名称": "赛",
        "SP消耗量": 4,
        "目标": "单体",
        "数值伤害": 40,
        "打击次数": 1,
        "命中几率": 99,
        "效果": null,
        "技能独有": "No",
        "描述": "对一名敌人造成念动属性的少量伤害",
        "校正伤害": 6.32,
        "平均伤害": "",
        "ID (Dec)": "",
        "暴击机率": "",
        "HP消耗量": "",
        "属性": "念动"
    },
    {
        "技能名称": "赛欧",
        "SP消耗量": 8,
        "目标": "单体",
        "数值伤害": 100,
        "打击次数": 1,
        "命中几率": 99,
        "效果": null,
        "技能独有": "No",
        "描述": "对一名敌人造成念动属性的中量伤害",
        "校正伤害": 10.0,
        "平均伤害": "",
        "ID (Dec)": "",
        "暴击机率": "",
        "HP消耗量": "",
        "属性": "念动"
    },
    {
        "技能名称": "赛达因",
        "SP消耗量": 12,
        "目标": "单体",
        "数值伤害": 160,
        "打击次数": 1,
        "命中几率": 99,
        "效果": null,
        "技能独有": "No",
        "描述": "对一名敌人造成念动属性的大量伤害",
        "校正伤害": 12.65,
        "平均伤害": "",
        "ID (Dec)": "",
        "暴击机率": "",
        "HP消耗量": "",
        "属性": "念动"
    },
    {
        "技能名称": "念动波",
        "SP消耗量": 48,
        "目标": "单体",
        "数值伤害": 200,
        "打击次数": 1,
        "命中几率": 98,
        "效果": null,
        "技能独有": "No",
        "描述": "对一名敌人造成念动属性的特大伤害",
        "校正伤害": 14.14,
        "平均伤害": "",
        "ID (Dec)": "",
        "暴击机率": "",
        "HP消耗量": "",
        "属性": "念动"
    },
    {
        "技能名称": "玛哈赛",
        "SP消耗量": 10,
        "目标": "全体",
        "数值伤害": 40,
        "打击次数": 1,
        "命中几率": 95,
        "效果": null,
        "技能独有": "No",
        "描述": "对所有敌人造成念动属性的少量伤害",
        "校正伤害": 6.32,
        "平均伤害": "",
        "ID (Dec)": "",
        "暴击机率": "",
        "HP消耗量": "",
        "属性": "念动"
    },
    {
        "技能名称": "玛哈赛欧",
        "SP消耗量": 16,
        "目标": "全体",
        "数值伤害": 100,
        "打击次数": 1,
        "命中几率": 95,
        "效果": null,
        "技能独有": "No",
        "描述": "对所有敌人造成念动属性的中量伤害",
        "校正伤害": 10.0,
        "平均伤害": "",
        "ID (Dec)": "",
        "暴击机率": "",
        "HP消耗量": "",
        "属性": "念动"
    },
    {
        "技能名称": "玛哈塞达因",
        "SP消耗量": 22,
        "目标": "全体",
        "数值伤害": 160,
        "打击次数": 1,
        "命中几率": 95,
        "效果": null,
        "技能独有": "No",
        "描述": "对所有敌人造成念动属性的大量伤害",
        "校正伤害": 12.65,
        "平均伤害": "",
        "ID (Dec)": "",
        "暴击机率": "",
        "HP消耗量": "",
        "属性": "念动"
    },
    {
        "技能名称": "念动力",
        "SP消耗量": 54,
        "目标": "全体",
        "数值伤害": 180,
        "打击次数": 1,
        "命中几率": 95,
        "效果": null,
        "技能独有": "No",
        "描述": "对所有敌人造成念动属性的特大伤害",
        "校正伤害": 13.42,
        "平均伤害": "",
        "ID (Dec)": "",
        "暴击机率": "",
        "HP消耗量": "",
        "属性": "念动"
    },
    {
        "技能名称": "克哈",
        "SP消耗量": 4,
        "目标": "单体",
        "数值伤害": 50,
        "打击次数": 1,
        "命中几率": 99,
        "效果": null,
        "技能独有": "No",
        "描述": "对一名敌人造成祝福属性的少量伤害",
        "校正伤害": 7.07,
        "平均伤害": "",
        "ID (Dec)": "",
        "暴击机率": "",
        "HP消耗量": "",
        "属性": "祝福"
    },
    {
        "技能名称": "克加",
        "SP消耗量": 8,
        "目标": "单体",
        "数值伤害": 120,
        "打击次数": 1,
        "命中几率": 99,
        "效果": null,
        "技能独有": "No",
        "描述": "对一名敌人造成祝福属性的中量伤害",
        "校正伤害": 10.95,
        "平均伤害": "",
        "ID (Dec)": "",
        "暴击机率": "",
        "HP消耗量": "",
        "属性": "祝福"
    },
    {
        "技能名称": "克加翁",
        "SP消耗量": 12,
        "目标": "单体",
        "数值伤害": 190,
        "打击次数": 1,
        "命中几率": 99,
        "效果": null,
        "技能独有": "No",
        "描述": "对一名敌人造成祝福属性的大量伤害",
        "校正伤害": 13.78,
        "平均伤害": "",
        "ID (Dec)": "",
        "暴击机率": "",
        "HP消耗量": "",
        "属性": "祝福"
    },
    {
        "技能名称": "玛哈克哈",
        "SP消耗量": 10,
        "目标": "全体",
        "数值伤害": 50,
        "打击次数": 1,
        "命中几率": 98,
        "效果": null,
        "技能独有": "No",
        "描述": "对所有敌人造成祝福属性的少量伤害",
        "校正伤害": 7.07,
        "平均伤害": "",
        "ID (Dec)": "",
        "暴击机率": "",
        "HP消耗量": "",
        "属性": "祝福"
    },
    {
        "技能名称": "玛哈克加",
        "SP消耗量": 16,
        "目标": "全体",
        "数值伤害": 120,
        "打击次数": 1,
        "命中几率": 95,
        "效果": null,
        "技能独有": "No",
        "描述": "对所有敌人造成祝福属性的中量伤害",
        "校正伤害": 10.95,
        "平均伤害": "",
        "ID (Dec)": "",
        "暴击机率": "",
        "HP消耗量": "",
        "属性": "祝福"
    },
    {
        "技能名称": "玛哈克加翁",
        "SP消耗量": 22,
        "目标": "全体",
        "数值伤害": 190,
        "打击次数": 1,
        "命中几率": 95,
        "效果": null,
        "技能独有": "No",
        "描述": "对所有敌人造成祝福属性的大量伤害",
        "校正伤害": 13.78,
        "平均伤害": "",
        "ID (Dec)": "",
        "暴击机率": "",
        "HP消耗量": "",
        "属性": "祝福"
    },
    {
        "技能名称": "神之审判",
        "SP消耗量": 38,
        "目标": "单体",
        "数值伤害": 50,
        "打击次数": 1,
        "命中几率": 95,
        "效果": "现有HP减半",
        "技能独有": "No",
        "描述": "对一名敌人发动祝福属性攻击使其HP变为1/2",
        "校正伤害": "Null",
        "平均伤害": "",
        "ID (Dec)": "",
        "暴击机率": "",
        "HP消耗量": "",
        "属性": "祝福"
    },
    {
        "技能名称": "哈玛",
        "SP消耗量": 6,
        "目标": "单体",
        "数值伤害": 1,
        "打击次数": 1,
        "命中几率": 100,
        "效果": "即死 (25%)",
        "技能独有": "No",
        "描述": "低概率对一名敌人造成祝福属性的即死效果",
        "校正伤害": "Null",
        "平均伤害": "",
        "ID (Dec)": "",
        "暴击机率": "",
        "HP消耗量": "",
        "属性": "祝福"
    },
    {
        "技能名称": "哈玛翁",
        "SP消耗量": 12,
        "目标": "单体",
        "数值伤害": 1,
        "打击次数": 1,
        "命中几率": 100,
        "效果": "即死 (50%)",
        "技能独有": "No",
        "描述": "中概率对一名敌人造成祝福属性的即死效果",
        "校正伤害": "Null",
        "平均伤害": "",
        "ID (Dec)": "",
        "暴击机率": "",
        "HP消耗量": "",
        "属性": "祝福"
    },
    {
        "技能名称": "玛翰玛",
        "SP消耗量": 14,
        "目标": "全体",
        "数值伤害": 1,
        "打击次数": 1,
        "命中几率": 100,
        "效果": "即死 (30%)",
        "技能独有": "No",
        "描述": "低概率对所有敌人造成祝福属性的即死效果",
        "校正伤害": "Null",
        "平均伤害": "",
        "ID (Dec)": "",
        "暴击机率": "",
        "HP消耗量": "",
        "属性": "祝福"
    },
    {
        "技能名称": "玛翰玛翁",
        "SP消耗量": 26,
        "目标": "全体",
        "数值伤害": 1,
        "打击次数": 1,
        "命中几率": 100,
        "效果": "即死 (50%)",
        "技能独有": "No",
        "描述": "中概率对所有敌人造成祝福属性的即死效果",
        "校正伤害": "Null",
        "平均伤害": "",
        "ID (Dec)": "",
        "暴击机率": "",
        "HP消耗量": "",
        "属性": "祝福"
    },
    {
        "技能名称": "回转讲道",
        "SP消耗量": 40,
        "目标": "全体",
        "数值伤害": 1,
        "打击次数": 1,
        "命中几率": 100,
        "效果": "即死 (70%)",
        "技能独有": "大僧正",
        "描述": "高概率对所有敌人造成祝福属性的即死效果",
        "校正伤害": "Null",
        "平均伤害": "",
        "ID (Dec)": "",
        "暴击机率": "",
        "HP消耗量": "",
        "属性": "祝福"
    },
    {
        "技能名称": "辉箭",
        "SP消耗量": 22,
        "目标": "全体",
        "数值伤害": 15,
        "打击次数": 1649376000000,
        "命中几率": 90,
        "效果": null,
        "技能独有": "辉夜(贼神)",
        "描述": "对所有敌人造成4-8次祝福属性的少量伤害",
        "校正伤害": "15.49-30.98",
        "平均伤害": "",
        "ID (Dec)": "",
        "暴击机率": "",
        "HP消耗量": "",
        "属性": "祝福"
    },
    {
        "技能名称": "耶哈",
        "SP消耗量": 4,
        "目标": "单体",
        "数值伤害": 50,
        "打击次数": 1,
        "命中几率": 99,
        "效果": null,
        "技能独有": "No",
        "描述": "对一名敌人造成咒怨属性的少量伤害",
        "校正伤害": 7.07,
        "平均伤害": "",
        "ID (Dec)": "",
        "暴击机率": "",
        "HP消耗量": "",
        "属性": "诅咒"
    },
    {
        "技能名称": "耶加",
        "SP消耗量": 8,
        "目标": "单体",
        "数值伤害": 120,
        "打击次数": 1,
        "命中几率": 99,
        "效果": null,
        "技能独有": "No",
        "描述": "对一名敌人造成咒怨属性的中量伤害",
        "校正伤害": 10.95,
        "平均伤害": "",
        "ID (Dec)": "",
        "暴击机率": "",
        "HP消耗量": "",
        "属性": "诅咒"
    },
    {
        "技能名称": "耶加翁",
        "SP消耗量": 12,
        "目标": "单体",
        "数值伤害": 190,
        "打击次数": 1,
        "命中几率": 99,
        "效果": null,
        "技能独有": "No",
        "描述": "对一名敌人造成咒怨属性的大量伤害",
        "校正伤害": 13.78,
        "平均伤害": "",
        "ID (Dec)": "",
        "暴击机率": "",
        "HP消耗量": "",
        "属性": "诅咒"
    },
    {
        "技能名称": "玛哈耶哈",
        "SP消耗量": 10,
        "目标": "全体",
        "数值伤害": 50,
        "打击次数": 1,
        "命中几率": 98,
        "效果": null,
        "技能独有": "No",
        "描述": "对所有敌人造成咒怨属性的少量伤害",
        "校正伤害": 7.07,
        "平均伤害": "",
        "ID (Dec)": "",
        "暴击机率": "",
        "HP消耗量": "",
        "属性": "诅咒"
    },
    {
        "技能名称": "玛哈耶加",
        "SP消耗量": 16,
        "目标": "全体",
        "数值伤害": 120,
        "打击次数": 1,
        "命中几率": 95,
        "效果": null,
        "技能独有": "No",
        "描述": "对所有敌人造成咒怨属性的中量伤害",
        "校正伤害": 10.95,
        "平均伤害": "",
        "ID (Dec)": "",
        "暴击机率": "",
        "HP消耗量": "",
        "属性": "诅咒"
    },
    {
        "技能名称": "玛哈耶加翁",
        "SP消耗量": 22,
        "目标": "全体",
        "数值伤害": 190,
        "打击次数": 1,
        "命中几率": 95,
        "效果": null,
        "技能独有": "No",
        "描述": "对所有敌人造成咒怨属性的大量伤害",
        "校正伤害": 13.78,
        "平均伤害": "",
        "ID (Dec)": "",
        "暴击机率": "",
        "HP消耗量": "",
        "属性": "诅咒"
    },
    {
        "技能名称": "恶魔审判",
        "SP消耗量": 38,
        "目标": "单体",
        "数值伤害": 50,
        "打击次数": 1,
        "命中几率": 95,
        "效果": "现有HP减半",
        "技能独有": "No",
        "描述": "对一名敌人发动咒怨属性攻击使其HP变为1/2",
        "校正伤害": "Null",
        "平均伤害": "",
        "ID (Dec)": "",
        "暴击机率": "",
        "HP消耗量": "",
        "属性": "诅咒"
    },
    {
        "技能名称": "姆多",
        "SP消耗量": 6,
        "目标": "单体",
        "数值伤害": 1,
        "打击次数": 1,
        "命中几率": 100,
        "效果": "即死 (25%)",
        "技能独有": "No",
        "描述": "低概率对一名敌人造成咒怨属性的即死效果",
        "校正伤害": "Null",
        "平均伤害": "",
        "ID (Dec)": "",
        "暴击机率": "",
        "HP消耗量": "",
        "属性": "诅咒"
    },
    {
        "技能名称": "姆多翁",
        "SP消耗量": 12,
        "目标": "单体",
        "数值伤害": 1,
        "打击次数": 1,
        "命中几率": 100,
        "效果": "即死 (50%)",
        "技能独有": "No",
        "描述": "中概率对一名敌人造成咒怨属性的即死效果",
        "校正伤害": "Null",
        "平均伤害": "",
        "ID (Dec)": "",
        "暴击机率": "",
        "HP消耗量": "",
        "属性": "诅咒"
    },
    {
        "技能名称": "玛哈姆多",
        "SP消耗量": 14,
        "目标": "全体",
        "数值伤害": 1,
        "打击次数": 1,
        "命中几率": 100,
        "效果": "即死 (30%)",
        "技能独有": "No",
        "描述": "低概率对所有敌人造成咒怨属性的即死效果",
        "校正伤害": "Null",
        "平均伤害": "",
        "ID (Dec)": "",
        "暴击机率": "",
        "HP消耗量": "",
        "属性": "诅咒"
    },
    {
        "技能名称": "玛哈姆多翁",
        "SP消耗量": 26,
        "目标": "全体",
        "数值伤害": 1,
        "打击次数": 1,
        "命中几率": 100,
        "效果": "即死(50%)",
        "技能独有": "No",
        "描述": "中概率对所有敌人造成咒怨属性的即死效果",
        "校正伤害": "Null",
        "平均伤害": "",
        "ID (Dec)": "",
        "暴击机率": "",
        "HP消耗量": "",
        "属性": "诅咒"
    },
    {
        "技能名称": "可以为我而死吗？",
        "SP消耗量": 40,
        "目标": "全体",
        "数值伤害": 1,
        "打击次数": 1,
        "命中几率": 100,
        "效果": "即死 (70%)",
        "技能独有": "爱丽丝",
        "描述": "高概率对所有敌人造成咒怨属性的即死效果",
        "校正伤害": "Null",
        "平均伤害": "",
        "ID (Dec)": "",
        "暴击机率": "",
        "HP消耗量": "",
        "属性": "诅咒"
    },
    {
        "技能名称": "祸津曼陀罗",
        "SP消耗量": 30,
        "目标": "全体",
        "数值伤害": 160,
        "打击次数": 1,
        "命中几率": 90,
        "效果": "绝望/恐惧/混乱(50%)",
        "技能独有": "祸津伊邪那歧 (贼神)",
        "描述": "对所有敌人造成咒怨属性的大量伤害 概率陷入混乱恐惧绝望状态",
        "校正伤害": 12.65,
        "平均伤害": "",
        "ID (Dec)": "",
        "暴击机率": "",
        "HP消耗量": "",
        "属性": "诅咒"
    },
    {
        "技能名称": "炼狱之翼",
        "SP消耗量": 30,
        "目标": "全体",
        "数值伤害": 210,
        "打击次数": 1,
        "命中几率": 90,
        "效果": null,
        "技能独有": "月读(贼神)",
        "描述": "对所有敌人造成咒怨属性的特大伤害",
        "校正伤害": 14.49,
        "平均伤害": "",
        "ID (Dec)": "",
        "暴击机率": "",
        "HP消耗量": "",
        "属性": "诅咒"
    },
    {
        "技能名称": "米吉多",
        "SP消耗量": 15,
        "目标": "全体",
        "数值伤害": 120,
        "打击次数": 1,
        "命中几率": 95,
        "效果": null,
        "技能独有": "No",
        "描述": "对所有敌人造成万能属性的中量伤害",
        "校正伤害": 10.95,
        "平均伤害": "",
        "ID (Dec)": "",
        "暴击机率": "",
        "HP消耗量": "",
        "属性": "万能"
    },
    {
        "技能名称": "米吉多拉",
        "SP消耗量": 24,
        "目标": "全体",
        "数值伤害": 180,
        "打击次数": 1,
        "命中几率": 95,
        "效果": null,
        "技能独有": "No",
        "描述": "对所有敌人造成万能属性的大量伤害",
        "校正伤害": 13.42,
        "平均伤害": "",
        "ID (Dec)": "",
        "暴击机率": "",
        "HP消耗量": "",
        "属性": "万能"
    },
    {
        "技能名称": "米吉多拉翁",
        "SP消耗量": 38,
        "目标": "全体",
        "数值伤害": 210,
        "打击次数": 1,
        "命中几率": 95,
        "效果": null,
        "技能独有": "No",
        "描述": "对所有敌人造成万能属性的特大伤害",
        "校正伤害": 14.49,
        "平均伤害": "",
        "ID (Dec)": "",
        "暴击机率": "",
        "HP消耗量": "",
        "属性": "万能"
    },
    {
        "技能名称": "吸血",
        "SP消耗量": 3,
        "目标": "单体",
        "数值伤害": 30,
        "打击次数": 1,
        "命中几率": 100,
        "效果": "吸取HP",
        "技能独有": "No",
        "描述": "吸取敌人的HP并转变为自己的HP",
        "校正伤害": 5.48,
        "平均伤害": "",
        "ID (Dec)": "",
        "暴击机率": "",
        "HP消耗量": "",
        "属性": "万能"
    },
    {
        "技能名称": "吸魔",
        "SP消耗量": 3,
        "目标": "单体",
        "数值伤害": 0,
        "打击次数": 1,
        "命中几率": 100,
        "效果": "吸取SP",
        "技能独有": "No",
        "描述": "吸取敌人的SP并转变为自己的SP",
        "校正伤害": "Null",
        "平均伤害": "",
        "ID (Dec)": "",
        "暴击机率": "",
        "HP消耗量": "",
        "属性": "万能"
    },
    {
        "技能名称": "污秽吐息",
        "SP消耗量": 8,
        "目标": "单体",
        "数值伤害": 0,
        "打击次数": 1,
        "命中几率": 100,
        "效果": "异常抗性下降",
        "技能独有": "No",
        "描述": "使一名敌人变得更容易陷入异常状态",
        "校正伤害": "Null",
        "平均伤害": "",
        "ID (Dec)": "",
        "暴击机率": "",
        "HP消耗量": "",
        "属性": "万能"
    },
    {
        "技能名称": "污秽空气",
        "SP消耗量": 5,
        "目标": "全体",
        "数值伤害": 0,
        "打击次数": 1,
        "命中几率": 100,
        "效果": "异常抗性下降",
        "技能独有": "No",
        "描述": "使敌我双方全体变得更容易陷入异常状态",
        "校正伤害": "Null",
        "平均伤害": "",
        "ID (Dec)": "",
        "暴击机率": "",
        "HP消耗量": "",
        "属性": "万能"
    },
    {
        "技能名称": "亡者喟叹",
        "SP消耗量": 28,
        "目标": "全体",
        "数值伤害": 0,
        "打击次数": 1,
        "命中几率": 100,
        "效果": "即死(100%)",
        "技能独有": "No",
        "描述": "对恐惧状态的敌人造成即死效果",
        "校正伤害": "Null",
        "平均伤害": "",
        "ID (Dec)": "",
        "暴击机率": "",
        "HP消耗量": "",
        "属性": "万能"
    },
    {
        "技能名称": "漆黑之蛇",
        "SP消耗量": 48,
        "目标": "单体",
        "数值伤害": 230,
        "打击次数": 1,
        "命中几率": 98,
        "效果": null,
        "技能独有": "撒旦/撒旦耶尔",
        "描述": "对一名敌人造成万能属性的特大伤害",
        "校正伤害": 15.17,
        "平均伤害": "",
        "ID (Dec)": "",
        "暴击机率": "",
        "HP消耗量": "",
        "属性": "万能"
    },
    {
        "技能名称": "拂晓明星",
        "SP消耗量": 55,
        "目标": "全体",
        "数值伤害": 230,
        "打击次数": 1,
        "命中几率": 95,
        "效果": null,
        "技能独有": "路西法",
        "描述": "对所有敌人造成万能属性的特大伤害",
        "校正伤害": 15.17,
        "平均伤害": "",
        "ID (Dec)": "",
        "暴击机率": "",
        "HP消耗量": "",
        "属性": "万能"
    },
    {
        "技能名称": "深渊之眼",
        "SP消耗量": 50,
        "目标": "全体",
        "数值伤害": 220,
        "打击次数": 1,
        "命中几率": 95,
        "效果": null,
        "技能独有": "哈斯塔",
        "描述": "对所有敌人造成万能属性的特大伤害",
        "校正伤害": 14.83,
        "平均伤害": "",
        "ID (Dec)": "",
        "暴击机率": "",
        "HP消耗量": "",
        "属性": "万能"
    },
    {
        "技能名称": "反抗之刃",
        "SP消耗量": 99,
        "目标": "单体",
        "数值伤害": 900,
        "打击次数": 1,
        "命中几率": 90,
        "效果": null,
        "技能独有": "赫里沃德",
        "描述": "对一名敌人造成万能属性的超特大伤害（对倒地的敌人伤害翻倍）",
        "校正伤害": "30/60",
        "平均伤害": "",
        "ID (Dec)": "",
        "暴击机率": "",
        "HP消耗量": "",
        "属性": "万能"
    },
    {
        "技能名称": "冥府之门",
        "SP消耗量": 32,
        "目标": "全体",
        "数值伤害": 160,
        "打击次数": 1,
        "命中几率": 90,
        "效果": "即死 (60%)",
        "技能独有": "塔纳托斯(贼神)",
        "描述": "对所有敌人造成万能属性的大量伤害 中概率造成即死效果",
        "校正伤害": 12.65,
        "平均伤害": "",
        "ID (Dec)": "",
        "暴击机率": "",
        "HP消耗量": "",
        "属性": "万能"
    },
    {
        "技能名称": "数万真言",
        "SP消耗量": 40,
        "目标": "全体",
        "数值伤害": 120,
        "打击次数": 3,
        "命中几率": 95,
        "效果": null,
        "技能独有": "伊邪那歧大神 (贼神)",
        "描述": "对所有敌人造成3次万能属性的大量伤害",
        "校正伤害": 32.86,
        "平均伤害": "",
        "ID (Dec)": "",
        "暴击机率": "",
        "HP消耗量": "",
        "属性": "万能"
    },
    {
        "技能名称": "致盲",
        "ID (Dec)": 80,
        "SP消耗量": 3,
        "目标": "单体",
        "数值伤害": 0,
        "打击次数": 1,
        "命中几率": 100,
        "效果": "晕眩(70%)",
        "技能独有": "No",
        "描述": "高概率使一名敌人陷入晕眩状态",
        "平均伤害": "",
        "暴击机率": "",
        "HP消耗量": "",
        "校正伤害": "",
        "属性": "异常"
    },
    {
        "技能名称": "黑夜闪光",
        "ID (Dec)": 81,
        "SP消耗量": 8,
        "目标": "全体",
        "数值伤害": 0,
        "打击次数": 1,
        "命中几率": 100,
        "效果": "晕眩(50%)",
        "技能独有": "No",
        "描述": "中概率使所有敌人陷入晕眩状态",
        "平均伤害": "",
        "暴击机率": "",
        "HP消耗量": "",
        "校正伤害": "",
        "属性": "异常"
    },
    {
        "技能名称": "普林帕",
        "ID (Dec)": 82,
        "SP消耗量": 3,
        "目标": "单体",
        "数值伤害": 0,
        "打击次数": 1,
        "命中几率": 100,
        "效果": "混乱(70%)",
        "技能独有": "No",
        "描述": "高概率使一名敌人陷入混乱状态",
        "平均伤害": "",
        "暴击机率": "",
        "HP消耗量": "",
        "校正伤害": "",
        "属性": "异常"
    },
    {
        "技能名称": "颠塔拉弗",
        "ID (Dec)": 83,
        "SP消耗量": 8,
        "目标": "全体",
        "数值伤害": 0,
        "打击次数": 1,
        "命中几率": 100,
        "效果": "混乱(50%)",
        "技能独有": "No",
        "描述": "中概率使所有敌人陷入混乱状态",
        "平均伤害": "",
        "暴击机率": "",
        "HP消耗量": "",
        "校正伤害": "",
        "属性": "异常"
    },
    {
        "技能名称": "恶魔之触",
        "ID (Dec)": 84,
        "SP消耗量": 3,
        "目标": "单体",
        "数值伤害": 0,
        "打击次数": 1,
        "命中几率": 100,
        "效果": "恐惧(70%)",
        "技能独有": "No",
        "描述": "高概率使一名敌人陷入恐惧状态",
        "平均伤害": "",
        "暴击机率": "",
        "HP消耗量": "",
        "校正伤害": "",
        "属性": "异常"
    },
    {
        "技能名称": "恶魔微笑",
        "ID (Dec)": 85,
        "SP消耗量": 8,
        "目标": "全体",
        "数值伤害": 0,
        "打击次数": 1,
        "命中几率": 100,
        "效果": "恐惧(50%)",
        "技能独有": "No",
        "描述": "中概率使所有敌人陷入恐惧状态",
        "平均伤害": "",
        "暴击机率": "",
        "HP消耗量": "",
        "校正伤害": "",
        "属性": "异常"
    },
    {
        "技能名称": "玛卡加玛",
        "ID (Dec)": 86,
        "SP消耗量": 3,
        "目标": "单体",
        "数值伤害": 0,
        "打击次数": 1,
        "命中几率": 100,
        "效果": "遗忘(70%)",
        "技能独有": "No",
        "描述": "高概率使一名敌人陷入遗忘状态",
        "平均伤害": "",
        "暴击机率": "",
        "HP消耗量": "",
        "校正伤害": "",
        "属性": "异常"
    },
    {
        "技能名称": "玛卡加玛翁",
        "ID (Dec)": 87,
        "SP消耗量": 8,
        "目标": "全体",
        "数值伤害": 0,
        "打击次数": 1,
        "命中几率": 100,
        "效果": "遗忘(50%)",
        "技能独有": "No",
        "描述": "中概率使所有敌人陷入遗忘状态",
        "平均伤害": "",
        "暴击机率": "",
        "HP消耗量": "",
        "校正伤害": "",
        "属性": "异常"
    },
    {
        "技能名称": "永眠",
        "ID (Dec)": 90,
        "SP消耗量": 3,
        "目标": "单体",
        "数值伤害": 0,
        "打击次数": 1,
        "命中几率": 100,
        "效果": "睡眠(70%)",
        "技能独有": "No",
        "描述": "高概率使一名敌人陷入睡眠状态",
        "平均伤害": "",
        "暴击机率": "",
        "HP消耗量": "",
        "校正伤害": "",
        "属性": "异常"
    },
    {
        "技能名称": "摇篮曲",
        "ID (Dec)": 91,
        "SP消耗量": 8,
        "目标": "全体",
        "数值伤害": 0,
        "打击次数": 1,
        "命中几率": 100,
        "效果": "睡眠(50%)",
        "技能独有": "No",
        "描述": "中概率使所有敌人陷入睡眠状态",
        "平均伤害": "",
        "暴击机率": "",
        "HP消耗量": "",
        "校正伤害": "",
        "属性": "异常"
    },
    {
        "技能名称": "挑衅",
        "ID (Dec)": 92,
        "SP消耗量": 3,
        "目标": "单体",
        "数值伤害": 0,
        "打击次数": 1,
        "命中几率": 100,
        "效果": "狂怒(70%)",
        "技能独有": "No",
        "描述": "高概率使一名敌人陷入狂怒状态",
        "平均伤害": "",
        "暴击机率": "",
        "HP消耗量": "",
        "校正伤害": "",
        "属性": "异常"
    },
    {
        "技能名称": "宣战布告",
        "ID (Dec)": 93,
        "SP消耗量": 8,
        "目标": "全体",
        "数值伤害": 0,
        "打击次数": 1,
        "命中几率": 100,
        "效果": "狂怒(50%)",
        "技能独有": "No",
        "描述": "中概率使所有敌人陷入狂怒状态",
        "平均伤害": "",
        "暴击机率": "",
        "HP消耗量": "",
        "校正伤害": "",
        "属性": "异常"
    },
    {
        "技能名称": "不吉的话语",
        "ID (Dec)": 94,
        "SP消耗量": 3,
        "目标": "单体",
        "数值伤害": 0,
        "打击次数": 1,
        "命中几率": 100,
        "效果": "绝望(70%)",
        "技能独有": "No",
        "描述": "高概率使一名敌人陷入绝望状态",
        "平均伤害": "",
        "暴击机率": "",
        "HP消耗量": "",
        "校正伤害": "",
        "属性": "异常"
    },
    {
        "技能名称": "深渊的波动",
        "ID (Dec)": 95,
        "SP消耗量": 8,
        "目标": "全体",
        "数值伤害": 0,
        "打击次数": 1,
        "命中几率": 100,
        "效果": "绝望(50%)",
        "技能独有": "No",
        "描述": "中概率使所有敌人陷入绝望状态",
        "平均伤害": "",
        "暴击机率": "",
        "HP消耗量": "",
        "校正伤害": "",
        "属性": "异常"
    },
    {
        "技能名称": "马琳卡琳",
        "ID (Dec)": 96,
        "SP消耗量": 3,
        "目标": "单体",
        "数值伤害": 0,
        "打击次数": 1,
        "命中几率": 100,
        "效果": "洗脑(70%)",
        "技能独有": "No",
        "描述": "高概率使一名敌人陷入洗脑状态",
        "平均伤害": "",
        "暴击机率": "",
        "HP消耗量": "",
        "校正伤害": "",
        "属性": "异常"
    },
    {
        "技能名称": "精神污染",
        "ID (Dec)": 97,
        "SP消耗量": 8,
        "目标": "全体",
        "数值伤害": 0,
        "打击次数": 1,
        "命中几率": 100,
        "效果": "洗脑(50%)",
        "技能独有": "No",
        "描述": "中概率使所有敌人陷入洗脑状态",
        "平均伤害": "",
        "暴击机率": "",
        "HP消耗量": "",
        "校正伤害": "",
        "属性": "异常"
    },
    {
        "技能名称": "幻影秀",
        "ID (Dec)": 716,
        "SP消耗量": 4,
        "目标": "全体",
        "数值伤害": 0,
        "打击次数": 1,
        "命中几率": 100,
        "效果": "睡眠(90%)",
        "技能独有": "劳尔",
        "描述": "高概率使所有敌人陷入睡眠状态",
        "平均伤害": "",
        "暴击机率": "",
        "HP消耗量": "",
        "校正伤害": "",
        "属性": "异常"
    }
]